markus_autotest_helpers_python/__init__.py
markus_autotest_helpers_python/code_properties.py
markus_autotest_helpers_python/coverage_analysis.py
markus_autotest_helpers_python/import_helpers.py
markus_autotest_helpers_python/test_case_validation.py
markus_autotest_helpers_python/test_case_validation_fixture.py
markus_autotest_helpers_python-0.1.0.dist-info/WHEEL
markus_autotest_helpers_python-0.1.0.dist-info/METADATA
markus_autotest_helpers_python-0.1.0.dist-info/RECORD
