Metadata-Version: 2.3
Name: markus-autotest-helpers-python
Version: 0.1.0
Summary: Helper functions and classes for executing Python unit tests
Author: Misha Schwartz, Alessio Di Sandro, Sophia Huynh, David Liu
Classifier: Programming Language :: Python :: 3
Classifier: License :: OSI Approved :: MIT License
Classifier: Operating System :: OS Independent
Requires-Dist: coverage
Requires-Dist: pytest
Requires-Dist: wrapt-timeout-decorator
Requires-Python: >=3.9
